rails_delegated_analyzer/__init__.py
rails_delegated_analyzer/main.py
rails_delegated_analyzer/prompts.py
rails_delegated_analyzer-2025.12.21150543.dist-info/METADATA
rails_delegated_analyzer-2025.12.21150543.dist-info/WHEEL
rails_delegated_analyzer-2025.12.21150543.dist-info/top_level.txt
rails_delegated_analyzer-2025.12.21150543.dist-info/RECORD
