Metadata-Version: 2.4
Name: rails-delegated-analyzer
Version: 2025.12.21150543
Summary: A new package would help developers understand and apply the Rails Delegated Type pattern by analyzing their text-based descriptions of database relationships or use cases. It would take a user's inpu
Author-email: rails-delegated-analyzer <hi@eugene.plus>
License: MIT
Project-URL: Homepage, https://github.com/chigwell/rails-delegated-analyzer
Requires-Python: >=3.9
Requires-Dist: langchain-llm7>=0.0.0
Requires-Dist: llmatch-messages>=0.0.0
Requires-Dist: langchain-core>=0.3.0
